ways/__init__.py
ways/api.py
ways/cache.py
ways/commander.py
ways/common.py
ways/connection.py
ways/descriptor.py
ways/dict_classes.py
ways/finder.py
ways/finder_common.py
ways/parse.py
ways/plugin.py
ways/resource.py
ways/situation.py
ways/trace.py
ways/core/.git
ways/core/.gitignore
ways/core/README.md
ways/core/__init__.py
ways/core/check.py
ways/core/compat.py
ways/core/grouping.py
ways/core/loop.py
ways/core/pathrip.py
ways/core/testsuite.py
ways/retro/.git
ways/retro/__init__.py
ways/retro/single.py
ways-0.1.0b1.dist-info/DESCRIPTION.rst
ways-0.1.0b1.dist-info/METADATA
ways-0.1.0b1.dist-info/RECORD
ways-0.1.0b1.dist-info/WHEEL
ways-0.1.0b1.dist-info/metadata.json
ways-0.1.0b1.dist-info/top_level.txt
